pools/abi.json
pools/test_utils.py
pools/uniswap.py
pools-20210424.dist-info/METADATA
pools-20210424.dist-info/WHEEL
pools-20210424.dist-info/entry_points.txt
pools-20210424.dist-info/top_level.txt
pools-20210424.dist-info/RECORD
