Metadata-Version: 2.1
Name: pools
Version: 20210424
Summary: Python library for pools liquidity providers
Home-page: https://github.com/AndreMiras/libpools
Author: Andre Miras
License: UNKNOWN
Platform: UNKNOWN
Requires-Dist: cachetools
Requires-Dist: gql (==3.0.0a3)
Requires-Dist: web3
Provides-Extra: dev
Requires-Dist: black ; extra == 'dev'
Requires-Dist: flake8 ; extra == 'dev'
Requires-Dist: isort ; extra == 'dev'
Requires-Dist: pytest ; extra == 'dev'
Requires-Dist: pytest-cov ; extra == 'dev'
Requires-Dist: tox ; extra == 'dev'
Requires-Dist: twine ; extra == 'dev'
Requires-Dist: wheel ; extra == 'dev'
